README.md
setup.py
ipublish/__init__.py
ipublish/core.py
ipublish/data.py
ipublish/pyipa.py
ipublish/util.py
ipublish.egg-info/PKG-INFO
ipublish.egg-info/SOURCES.txt
ipublish.egg-info/dependency_links.txt
ipublish.egg-info/entry_points.txt
ipublish.egg-info/not-zip-safe
ipublish.egg-info/requires.txt
ipublish.egg-info/top_level.txt