Metadata-Version: 1.0
Name: ipublish
Version: 1.0.7
Summary: ios 发布工具
Home-page: https://github.com/wangweicheng7/ipublish
Author: wang weicheng
Author-email: 809405366@qq.com
License: MIT
Platform: UNKNOWN
